vmux/__init__.py
vmux/__main__.py
vmux-1.1.dev14.dist-info/LICENSE
vmux-1.1.dev14.dist-info/METADATA
vmux-1.1.dev14.dist-info/WHEEL
vmux-1.1.dev14.dist-info/entry_points.txt
vmux-1.1.dev14.dist-info/top_level.txt
vmux-1.1.dev14.dist-info/RECORD
