Metadata-Version: 2.1
Name: vmux
Version: 1.1.dev14
Summary: vim/neovim/kakoune session handler within tmux
Home-page: https://github.com/jceb/vmux
Author: Jan Christoph Ebersbach
Author-email: jceb@e-jc.de
License: GPLv3
Platform: UNKNOWN
Classifier: License :: OSI Approved :: GNU General Public License v3 or later (GPLv3+)
Classifier: Programming Language :: Python
Requires-Dist: pynvim (>=0.3.2)
